rusaint/__init__.py
rusaint/librusaint_ffi.dylib
rusaint/rusaint.py
rusaint/rusaint_ffi.py
rusaint-0.14.0.dist-info/METADATA
rusaint-0.14.0.dist-info/WHEEL
rusaint-0.14.0.dist-info/RECORD
