Metadata-Version: 2.4
Name: rusaint
Version: 0.14.0
Classifier: Programming Language :: Rust
Classifier: Programming Language :: Python :: Implementation :: CPython
Classifier: Programming Language :: Python :: Implementation :: PyPy
Home-Page: https://eatsteak.dev
Author: Hyomin Koo <me@eatsteak.dev>
Author-email: Hyomin Koo <me@eatsteak.dev>
License: MIT
Requires-Python: >=3.8
